plugs_mail/__init__.py
plugs_mail/mail.py
plugs_mail/settings.py
plugs_mail/utils.py
plugs_mail/management/__init__.py
plugs_mail/management/commands/__init__.py
plugs_mail/management/commands/load_email_templates.py
plugs_mail/templates/__init__.py
plugs_mail/templates/base.html
plugs_mail/templatetags/__init__.py
plugs_mail/templatetags/emailtags.py
plugs_mail-0.2.0.dist-info/DESCRIPTION.rst
plugs_mail-0.2.0.dist-info/METADATA
plugs_mail-0.2.0.dist-info/RECORD
plugs_mail-0.2.0.dist-info/WHEEL
plugs_mail-0.2.0.dist-info/metadata.json
plugs_mail-0.2.0.dist-info/top_level.txt
