Metadata-Version: 2.0
Name: plugs-mail
Version: 0.2.0
Summary: Declarative and Templated Emails
Home-page: https://github.com/solocompt/plugs-mail
Author: Solo
Author-email: geral@solo.com.pt
License: MIT
Keywords: plugs-mail
Platform: UNKNOWN
Classifier: Development Status :: 3 - Alpha
Classifier: Framework :: Django :: 1.11
Classifier: Intended Audience :: Developers
Classifier: License :: OSI Approved :: MIT License
Classifier: Natural Language :: English
Classifier: Programming Language :: Python :: 3
Requires-Dist: cssselect (>=1.0.0)
Requires-Dist: django-post-office (<4.0.0,>=3.0.3)
Requires-Dist: plugs-core (<1.0.0,>=0.1.0)
